{"name":"Sassbeautify","tagline":"A Sublime Text plugin that beautifies Sass files.","body":"# SassBeautify\r\n\r\nhttps://sublime.wbond.net/packages/SassBeautify\r\n\r\nA Sublime Text plugin that beautifies Sass files. (Compatible with Sublime Text 2 & 3.)\r\n\r\n![ScreenShot](https://raw.github.com/badsyntax/SassBeautify/master/assets/screenshot.png)\r\n\r\n## Dependencies\r\n\r\nYou need to have sass installed. Read the [sass download page](http://sass-lang.com/download.html) to view the installation options.\r\n\r\n## Installation\r\n\r\n**Option 1 (recommended)**\r\n\r\nInstall via package control:\r\n\r\n1. Ensure you have package control installed, see here: https://sublime.wbond.net/installation\r\n2. Install the package: open up the command palette (ctrl/cmd + shift + p), execute the following command:\r\n'Package Control: Install Package', then enter 'SassBeautify'\r\n\r\n**Option 2**\r\n\r\nManual download:\r\n\r\n1. Download the zip file file here: https://github.com/badsyntax/SassBeautify/archive/master.zip\r\n2. Unzip the archive, rename the 'SassBeautify-master' folder to 'SassBeautify' and move it into your\r\nSublime Text 'Packages' directory.\r\n\r\n## Usage\r\n\r\n**Default usage**\r\n\r\nRun the plugin from the command palette:\r\n\r\n1. Open the command palette (ctrl/cmd + shift + p)\r\n2. Enter 'SassBeautify'\r\n\r\n**Conversion usage**\r\n\r\nYou can use this plugin to convert from different types. For example, if you create a blank .scss file, then \r\ncopy in a block of CSS code, you can use this plugin to convert the CSS to SCSS. Note that the entire file \r\nwill have to be in the correct format for the conversion to work correctly.\r\n\r\nRun the conversion commands from the command palette:\r\n\r\n1. Open the command palette (ctrl/cmd + shift + p)\r\n2. Type 'SassBeautify'\r\n3. Choose one of the following options:\r\n  * Convert from CSS to current type\r\n  * Convert from SCSS to current type\r\n  * Convert from SASS to current type\r\n\r\n## Settings\r\n\r\nOnce installed, you can customize how the beautification works by changing the package settings.\r\n\r\n1. Open the default settings from the preferences menu: `Preferences >> Package Settings >> SassBeautify >> Settings - Default`\r\n2. Copy the settings and paste them into your user settings file: `Preferences >> Package Settings >> SassBeautify >> Settings - User`\r\n3. Change the user settings.\r\n\r\n### Settings overview\r\n\r\nThe following settings can be adjusted:\r\n\r\n```javascript\r\n{\r\n  \"indent\": 4,        // How many spaces to use for each level of indentation. \"t\" means use hard tabs.\r\n  \"dasherize\": false, // Convert underscores to dashes.\r\n  \"old\": false,       // Output the old-style \":prop val\" property syntax. Only meaningful when generating Sass.\r\n  \"path\": false       // Custom environment PATH.\r\n}\r\n```\r\n\r\n## How it works\r\n\r\nThis plugin is simply a wrapper around the `sass-convert` utility. The `sass-convert `utility will *compile your Sass/Scss\r\nto Sass/Scss*, and thus there's a chance values might change. (For example, see [issue #7](https://github.com/badsyntax/SassBeautify/issues/7).) \r\n\r\n## Compatibility with RVM \r\n\r\n(This does not apply to Windows users.)\r\n\r\nRVM uses a shell login script to modify the environment PATH, so you will need to manually add this path to the package\r\nsettings if you want this plugin to use the same ruby and gem versions. \r\n\r\nTo get this plugin to work with RVM, follow the steps below:\r\n\r\n1. Open up terminal.\r\n2. Run the following `echo $PATH`\r\n3. Copy the entire PATH and add this to the package 'path' setting.\r\n\r\n## Issues\r\n\r\nThis plugin should work on Linux (tested on Ubuntu 12.04), Windows (tested on Windows 7) and OSX (tested on 10.5.7).\r\nPlease [create an issue](https://github.com/badsyntax/SassBeautify/issues) if you find it doesn't work\r\nas expected on your setup.\r\n\r\n## License\r\n\r\nLicensed under the MIT license. Created by [Richard Willis](http://badsyntax.co/)\r\n","google":"UA-1636725-37","note":"Don't delete this file! It's used internally to help with page regeneration."}